pytest_hoverfly/__init__.py
pytest_hoverfly/base.py
pytest_hoverfly/cert.pem
pytest_hoverfly/helpers.py
pytest_hoverfly/pytest_hoverfly.py
pytest_hoverfly-5.0.4.dist-info/entry_points.txt
pytest_hoverfly-5.0.4.dist-info/LICENSE
pytest_hoverfly-5.0.4.dist-info/WHEEL
pytest_hoverfly-5.0.4.dist-info/METADATA
pytest_hoverfly-5.0.4.dist-info/RECORD
