Metadata-Version: 2.1
Name: pytest-hoverfly
Version: 5.0.4
Summary: Simplify working with Hoverfly from pytest
Home-page: https://github.com/wrike/pytest-hoverfly
License: MIT
Keywords: hoverfly,pytest,tests
Author: Devops team at Wrike
Author-email: devops@team.wrike.com
Requires-Python: >=3.7,<4.0
Classifier: Framework :: Pytest
Classifier: License :: OSI Approved :: MIT License
Classifier: Programming Language :: Python :: 3
Classifier: Programming Language :: Python :: 3.7
Classifier: Programming Language :: Python :: 3.8
Requires-Dist: docker (>=5.0.3)
Requires-Dist: pytest (>=5.0)
Requires-Dist: requests (>=2.22.0)
Requires-Dist: typing_extensions (>=3.7.4)
Project-URL: Repository, https://github.com/wrike/pytest-hoverfly
